xywechatpad_binary/__init__.py
xywechatpad_binary/binaries/macos_x64/XYWechatPad
xywechatpad_binary-1.1.0.dist-info/METADATA
xywechatpad_binary-1.1.0.dist-info/WHEEL
xywechatpad_binary-1.1.0.dist-info/top_level.txt
xywechatpad_binary-1.1.0.dist-info/RECORD
